odoo/addons/energy_communities_api/README.md
odoo/addons/energy_communities_api/__init__.py
odoo/addons/energy_communities_api/__manifest__.py
odoo/addons/energy_communities_api/utils.py
odoo/addons/energy_communities_api/components/__init__.py
odoo/addons/energy_communities_api/components/base.py
odoo/addons/energy_communities_api/components/energy_community_api_info.py
odoo/addons/energy_communities_api/components/energy_project_api_info.py
odoo/addons/energy_communities_api/components/energy_selfconsumption_project.py
odoo/addons/energy_communities_api/components/opendata_api_info.py
odoo/addons/energy_communities_api/components/partner_api_info.py
odoo/addons/energy_communities_api/controllers/__init__.py
odoo/addons/energy_communities_api/controllers/energy_communities.py
odoo/addons/energy_communities_api/controllers/energy_selfconsumption.py
odoo/addons/energy_communities_api/controllers/opendata.py
odoo/addons/energy_communities_api/demo/energy_selfconsumption_app_demo.xml
odoo/addons/energy_communities_api/models/__init__.py
odoo/addons/energy_communities_api/models/account_move.py
odoo/addons/energy_communities_api/models/auth_jwt_validator.py
odoo/addons/energy_communities_api/models/ir_http.py
odoo/addons/energy_communities_api/models/res_partner.py
odoo/addons/energy_communities_api/models/res_users_role.py
odoo/addons/energy_communities_api/schemas/__init__.py
odoo/addons/energy_communities_api/schemas/base.py
odoo/addons/energy_communities_api/schemas/community.py
odoo/addons/energy_communities_api/schemas/energy_project.py
odoo/addons/energy_communities_api/schemas/invoice.py
odoo/addons/energy_communities_api/schemas/member.py
odoo/addons/energy_communities_api/schemas/network_info.py
odoo/addons/energy_communities_api/schemas/selfconsumption_project.py
odoo/addons/energy_communities_api/security/ir.model.access.csv
odoo/addons/energy_communities_api/security/ir_rule_data.xml
odoo/addons/energy_communities_api/security/res_users_role_data.xml
odoo_addon_energy_communities_api-16.0.0.4.3.dist-info/METADATA
odoo_addon_energy_communities_api-16.0.0.4.3.dist-info/WHEEL
odoo_addon_energy_communities_api-16.0.0.4.3.dist-info/top_level.txt
odoo_addon_energy_communities_api-16.0.0.4.3.dist-info/RECORD
