Metadata-Version: 2.1
Name: odoo-addon-energy_communities_api
Version: 16.0.0.4.3
Requires-Python: >=3.10
Requires-Dist: email_validator==2.2.0
Requires-Dist: extendable-pydantic==1.3.2
Requires-Dist: odoo-addon-auth_jwt>=16.0dev,<16.1dev
Requires-Dist: odoo-addon-base_rest>=16.0dev,<16.1dev
Requires-Dist: odoo-addon-base_rest_pydantic>=16.0dev,<16.1dev
Requires-Dist: odoo-addon-component>=16.0dev,<16.1dev
Requires-Dist: odoo-addon-energy_communities>=16.0dev,<16.1dev
Requires-Dist: odoo-addon-energy_selfconsumption>=16.0dev,<16.1dev
Requires-Dist: odoo-addon-pydantic>=16.0dev,<16.1dev
Requires-Dist: odoo>=16.0a,<16.1dev
Requires-Dist: pydantic==2.9.2
Summary: API/REST endpoints for energy communities
Home-page: https://git.coopdevs.org/coopdevs/comunitats-energetiques/odoo-ce
License: AGPL-3
Author: Coopdevs Treball SCCL & Som Energia SCCL & SomIT
Classifier: Programming Language :: Python
Classifier: Framework :: Odoo
Classifier: Framework :: Odoo :: 16.0
Classifier: License :: OSI Approved :: GNU Affero General Public License v3
